<Properties StartupConfiguration="{CD6E4C3D-F2F9-4C5E-9AEA-BF7DDD449B85}|Default">
  <MonoDevelop.Ide.Workbench ActiveDocument="ElSerajElMoneer/Client/Pages/Taghreda.razor">
    <Files>
      <File FileName="ElSerajElMoneer/Server/Controllers/TaghredatElSeraController.cs" Line="19" Column="17" />
      <File FileName="ElSerajElMoneer/Client/Pages/Taghredat.razor" Line="531" Column="38" />
      <File FileName="ElSerajElMoneer/Server/Services/ITaghredatElSeraService.cs" Line="13" Column="67" />
      <File FileName="ElSerajElMoneer/Server/Services/TaghredatElSeraService.cs" Line="20" Column="80" />
      <File FileName="ElSerajElMoneer/Client/Pages/Taghreda.razor" Line="480" Column="90" />
    </Files>
    <Pads>
      <Pad Id="ProjectPad">
        <State name="__root__">
          <Node name="ElSerajElMoneer" expanded="True">
            <Node name="ElSerajElMoneer.Client" expanded="True">
              <Node name="Pages" expanded="True">
                <Node name="Taghreda.razor" selected="True" />
              </Node>
              <Node name="Shared" expanded="True" />
            </Node>
            <Node name="ElSerajElMoneer.Core" expanded="True" />
            <Node name="ElSerajElMoneer.Data" expanded="True" />
            <Node name="ElSerajElMoneer.Server" expanded="True">
              <Node name="Controllers" expanded="True" />
              <Node name="Dtos" expanded="True" />
              <Node name="Extension" expanded="True" />
              <Node name="Repositories" expanded="True" />
              <Node name="Services" expanded="True" />
            </Node>
            <Node name="ElSerajElMoneer.Shared" expanded="True" />
          </Node>
        </State>
      </Pad>
    </Pads>
  </MonoDevelop.Ide.Workbench>
  <MonoDevelop.Ide.DebuggingService.PinnedWatches />
  <MonoDevelop.Ide.Workspace ActiveConfiguration="Debug" />
  <MonoDevelop.Ide.ItemProperties.ElSerajElMoneer.Server PreferredExecutionTarget="/Applications/Google Chrome.app" />
  <MonoDevelop.Ide.DebuggingService.Breakpoints>
    <BreakpointStore />
  </MonoDevelop.Ide.DebuggingService.Breakpoints>
  <MultiItemStartupConfigurations />
</Properties>